Workbook

Sheet Read Me & Status
A1: FIFG 2027 Masters, Majors and 500 — Bid Response & Comparison Workbook
A2: Companion response file to the official 2027 bid document. The Word bid document remains the controlling requirements document.
A4: How to use: complete the yellow response cells and use the dropdowns where available. Enter comparable financial amounts in EUR. Use evidence or comments to explain every No. Countries must submit this Excel file and may also send a presentation of the tournament proposal.
A7: Submission information
A8: Full bid deadline | B8: October 30, 2026 | C8: Clarifications | D8: Until October 25, 2026 | E8: Host decisions | F8: November 15, 2026
A9: Submit to | B9: info@fifg.org and board@fifg.org | E9: Currency | F9: EUR
A10: Open Date form | B10: https://forms.gle/677Wtc64oCaXQd166
A12: Key calendar and eligibility rules
A13: 1 | B13: No FIFG World Tour tournament may take place during the 2027 FIFG World Club Trophy.
A14: 2 | B14: Countries should first try to resolve an Open-date clash by agreement. If they cannot agree, the country with more FIFG World Tour licences has priority.
A15: 3 | B15: A region needs at least 260 World Tour licences to organize a Major; a Masters region needs at least 500.
A17: Bid completion status
A18: Metric | B18: Result | D18: Completion | F18: Colour guide
A19: Required items completed | B19: =COUNTIF('Bidder Details'!D5:D16,"Complete")+COUNTIF('Dates & Event'!D5:D11,"Complete")+COUNTIF('Courses & Operations'!D5:D14,"Complete")+COUNTIF('Fees & Services'!D5:D12,"Complete")+COUNTIF('Media & Funding'!D8:D16,"Complete")+COUNTIF('Compliance & Variances'!E6:E13,"Complete")+COUNTIF('Bidder Details'!D5:D16,"Variance")+COUNTIF('Dates & Event'!D5:D11,"Variance")+COUNTIF('Courses & Operations'!D5:D14,"Variance")+COUNTIF('Fees & Services'!D5:D12,"Variance")+COUNTIF('Media & Funding'!D8:D16,"Variance")+COUNTIF('Compliance & Variances'!E6:E13,"Variance") -> 37 | D19: =IF((B19+B20)=0,0,B19/(B19+B20)) -> 0.75510204 | F19: Yellow = bidder input
A20: Required items remaining | B20: =COUNTIF('Bidder Details'!D5:D16,"Missing")+COUNTIF('Dates & Event'!D5:D11,"Missing")+COUNTIF('Courses & Operations'!D5:D14,"Missing")+COUNTIF('Fees & Services'!D5:D12,"Missing")+COUNTIF('Media & Funding'!D8:D16,"Missing")+COUNTIF('Compliance & Variances'!E6:E13,"Missing") -> 12 | F20: Grey / green = automatic result
A21: Declared variances | B21: =COUNTIF('Bidder Details'!D5:D16,"Variance")+COUNTIF('Dates & Event'!D5:D11,"Variance")+COUNTIF('Courses & Operations'!D5:D14,"Variance")+COUNTIF('Fees & Services'!D5:D12,"Variance")+COUNTIF('Media & Funding'!D8:D16,"Variance")+COUNTIF('Compliance & Variances'!E6:E13,"Variance") -> 0 | F21: Explain every variance
A22: Overall readiness | B22: =IF(B20>0,"Outstanding items",IF(B21>0,"Review variances","Ready for submission")) -> Outstanding items | F22: Presentation is optional
A24: Workbook sections
A25: No. | B25: Sheet | C25: Purpose | D25: Status | E25: Action | F25: Note
A26: 1 | B26: Bidder Details | C26: Applicant, event level, licence profile and hosting experience | D26: Mandatory | E26: Start here | F26: Complete all required fields
A27: 2 | B27: Dates & Event | C27: Open dates, rounds, capacity and calendar confirmations | D27: Mandatory | E27: Submit the Open Date form | F27: Deadline: October 19
A28: 3 | B28: Courses & Operations | C28: Courses, facilities, staffing, safety and transport | D28: Mandatory | E28: Confirm capacity | F28: Second course depends on level
A29: 4 | B29: Fees & Services | C29: Fees, inclusions, meals, prize money and rates | D29: Mandatory | E29: Show value for price | F29: Amounts in EUR
A30: 5 | B30: Media & Funding | C30: Broadcast budget, financing and content delivery | D30: Mandatory | E30: State guaranteed support | F30: Approx. EUR 25,000 if selected
A31: 6 | B31: Compliance & Variances | C31: Key confirmations, evidence and comments | D31: Mandatory | E31: Explain every No | F31: Use the comments column
A32: 7 | B32: Comparison Summary | C32: Automatic bid snapshot | D32: FIFG use | E32: Do not edit formula cells | F32: Updates automatically

Sheet Bidder Details
A1: FIFG 2027 Masters, Majors and 500 — Bidder Details
A2: Complete the yellow cells and keep responses concise. A separate tournament presentation may be submitted with the completed workbook.
A4: Requirement / question | B4: Bidder response | C4: Required? | D4: Status | E4: Evidence / comments
A5: FIFG Member Country | B5: Italy | C5: Yes | D5: =IF(C5="No","Optional",IF(B5<>"","Complete","Missing")) -> Complete
A6: FIFG region | B6: Region 3 (Europe) | C6: Yes | D6: =IF(C6="No","Optional",IF(B6<>"","Complete","Missing")) -> Complete
A7: Event level requested | B7: FIFG 500 | C7: Yes | D7: =IF(C7="No","Optional",IF(B7<>"","Complete","Missing")) -> Complete
A8: Proposed Open / tournament name | B8: Italian FootGolf Open 2027 – Rome (FIFG 500) | C8: Yes | D8: =IF(C8="No","Optional",IF(B8<>"","Complete","Missing")) -> Complete | E8: Main 2027 national Open of Italy.
A9: Host city, region and country | B9: Rome, Lazio, Italy – Golf Club Parco de' Medici | C9: Yes | D9: =IF(C9="No","Optional",IF(B9<>"","Complete","Missing")) -> Complete | E9: Venue in the south-west of Rome (EUR / Magliana area), between Rome city centre and Fiumicino Airport.
A10: Bid leader — name and role | C10: Yes | D10: =IF(C10="No","Optional",IF(B10<>"","Complete","Missing")) -> Missing
A11: Bid leader email and telephone | C11: Yes | D11: =IF(C11="No","Optional",IF(B11<>"","Complete","Missing")) -> Missing
A12: World Tour licences in the Member Country | C12: Yes | D12: =IF(C12="No","Optional",IF(B12<>"","Complete","Missing")) -> Missing
A13: Recreational licences in the Member Country | C13: Yes | D13: =IF(C13="No","Optional",IF(B13<>"","Complete","Missing")) -> Missing
A14: Women licences in the Member Country | C14: Yes | D14: =IF(C14="No","Optional",IF(B14<>"","Complete","Missing")) -> Missing
A15: Junior licences in the Member Country | C15: Yes | D15: =IF(C15="No","Optional",IF(B15<>"","Complete","Missing")) -> Missing
A16: Relevant hosting experience | C16: Yes | D16: =IF(C16="No","Optional",IF(B16<>"","Complete","Missing")) -> Missing

Sheet Dates & Event
A1: Dates & Event Format
A2: Enter the dates of the country's main 2027 Open. The Open Date form must be submitted by October 19, 2026.
A4: Requirement / question | B4: Bidder response | C4: Required? | D4: Status | E4: Evidence / comments
A5: Proposed start date (practice day) | B5: 2 July 2027 (official practice day) | C5: Yes | D5: =IF(C5="No","Optional",IF(B5<>"","Complete","Missing")) -> Complete | E5: Three days of course use: 2 July practice, 3–4 July competition.
A6: Main Open — proposed end date | B6: 4 July 2027 | C6: Yes | D6: =IF(C6="No","Optional",IF(B6<>"","Complete","Missing")) -> Complete | E6: Final round and closing ceremony on Sunday 4 July 2027.
A7: Number of competition rounds | B7: 2 | C7: Yes | D7: =IF(C7="No","Optional",IF(B7<>"","Complete","Missing")) -> Complete | E7: One round per day (3 and 4 July). Same number of rounds for all categories.
A8: Maximum field capacity | B8: 144 | C8: Yes | D8: =IF(C8="No","Optional",IF(B8<>"","Complete","Missing")) -> Complete | E8: 18-hole FootGolf layout, groups of 4, two-tee or shotgun start in two waves. Final field size subject to FIFG approval of the schedule.
A9: Open Date form submitted? https://forms.gle/677Wtc64oCaXQd166 | C9: Yes | D9: =IF(C9="No","Optional",IF(B9<>"","Complete","Missing")) -> Missing
A10: Open-date clash rule acknowledged | B10: Yes | C10: Yes | D10: =IF(C10="No","Optional",IF(B10<>"","Complete","Missing")) -> Complete | E10: Italy acknowledges the calendar coordination and Open-date clash rules (bid document §3.1).
A11: Alternative date window, if requested by FIFG | C11: No | D11: =IF(C11="No","Optional",IF(B11<>"","Complete","Missing")) -> Optional

Sheet Courses & Operations
A1: Courses & Operations
A2: Summarize course readiness, delivery capacity and the people responsible for safe tournament operations.
A4: Requirement / question | B4: Bidder response | C4: Required? | D4: Status | E4: Evidence / comments
A5: Course 1 — name and location | B5: Golf Club Parco de' Medici – Viale Salvatore Rebecchini 39, 00148 Rome (RM), Italy | C5: Yes | D5: =IF(C5="No","Optional",IF(B5<>"","Complete","Missing")) -> Complete | E5: 27-hole golf facility (White, Blue and Red nines) inside the Sheraton Rome Parco de' Medici complex. www.golfparcodemedici.it
A6: Course 1 — par, distance and capacity | B6: Planned 18-hole FootGolf layout, target par 72; capacity 144 players (2 waves of 18 groups of 4) | C6: Yes | D6: =IF(C6="No","Optional",IF(B6<>"","Complete","Missing")) -> Complete | E6: Final layout, length, tee positions and any temporary holes to be designed with the club and submitted for FIFG approval. The 27 golf holes leave room for a separate practice layout.
A7: Course 2 — name and location | C7: =IF(OR('Bidder Details'!B7="FIFG Masters",'Bidder Details'!B7="FIFG Major 1000"),"Yes","No") -> No | D7: =IF(C7="No","Optional",IF(B7<>"","Complete","Missing")) -> Optional
A8: Course 2 — par, distance and capacity | C8: =IF(OR('Bidder Details'!B7="FIFG Masters",'Bidder Details'!B7="FIFG Major 1000"),"Yes","No") -> No | D8: =IF(C8="No","Optional",IF(B8<>"","Complete","Missing")) -> Optional
A9: Clubhouse, changing rooms, toilets, parking, water, power and internet | B9: Clubhouse with restaurant and bar, changing rooms and toilets, large car park, mains power and Wi-Fi in the clubhouse; at least 2 drinking-water refill points and shaded rest areas on course. | C9: Yes | D9: =IF(C9="No","Optional",IF(B9<>"","Complete","Missing")) -> Complete | E9: Backup 4G/5G router, charging station and printer at the scoring area. Exclusive or protected use of the FootGolf holes during practice and competition to be agreed with the club.
A10: Will the event have a Tournament Director, Rules Director and accountable operational lead? | B10: Yes | C10: Yes | D10: =IF(C10="No","Optional",IF(B10<>"","Complete","Missing")) -> Complete | E10: Tournament Director, Rules Director and an English-speaking operational lead will be appointed by the Italian federation; organizational chart and names to be provided with the Host Agreement. Live scoring on BlueGolf.
A11: Will the event have starters, marshals, a scoring team and volunteers? | B11: Yes | C11: Yes | D11: =IF(C11="No","Optional",IF(B11<>"","Complete","Missing")) -> Complete | E11: At least 1 non-playing on-site operations staff member and 1 non-playing marshal (FIFG 500 minimum), plus trained starters, marshals, score reviewers and volunteers under a Volunteer Coordinator.
A12: Medical cover, risk assessment, emergency plan and insurance | B12: Yes – first-aid team and ambulance on site during practice and competition; written risk assessment, emergency action plan and public liability / event insurance. | C12: Yes | D12: =IF(C12="No","Optional",IF(B12<>"","Complete","Missing")) -> Complete | E12: Nearest emergency hospital: Ospedale Sant'Eugenio (EUR), approx. 5 km. Heat, lightning, severe weather, evacuation and suspension-of-play protocols included in the emergency plan.
A13: Will you offer accommodation, transfers, local transport and accessible options? | B13: Yes – recommended hotel on site (Sheraton Rome Parco de' Medici), airport and city transfers, golf carts for operations, accessible facilities. | C13: Yes | D13: =IF(C13="No","Optional",IF(B13<>"","Complete","Missing")) -> Complete | E13: Accommodation and transfers are optional packages, separate from the entry fee. Hotel and course are in the same complex, so no daily player transport is needed. Shuttle from Fiumicino/Ciampino and Rome Termini on request.
A14: Available daylight, evacuation and course-contingency plan | B14: Approx. 15 hours of daylight (sunrise ~05:40, sunset ~20:45). Heat plan with early tee times, water and shade; clubhouse used as evacuation shelter. | C14: Yes | D14: =IF(C14="No","Optional",IF(B14<>"","Complete","Missing")) -> Complete | E14: Early July in Rome is hot and dry (typical highs 30–33 °C). Contingency: shift tee times earlier, reduce to one wave, or move to reserve holes on the 27-hole site.

Sheet Fees & Services
A1: Entry Fees & Included Services
A2: Enter comparable amounts in EUR. For FIFG 500 tournaments and above, the green fee / entry fee must include all items listed below.
A4: Requirement / question | B4: Bidder response | C4: Required? | D4: Status | E4: Evidence / comments
A5: Standard entry fee amount per player (EUR) | B5: 230 | C5: Yes | D5: =IF(C5="No","Optional",IF(B5<>"","Complete","Missing")) -> Complete | E5: Standard fee, EUR 230 per player, from 1 April to 20 June 2027 (registration close). Entry-only option always available.
A6: Early-bird fee and validity dates | B6: EUR 200 – early-bird valid 1–31 March 2027 | C6: Yes | D6: =IF(C6="No","Optional",IF(B6<>"","Complete","Missing")) -> Complete | E6: Registration opens 1 March 2027 (within the 5-month limit). Opening communicated to all 2026 participants. Early-bird below the EUR 220 Region 3 cap and available for 31 days.
A7: Prize money / prize fund (EUR) | B7: 4000 | C7: Yes | D7: =IF(C7="No","Optional",IF(B7<>"","Complete","Missing")) -> Complete | E7: Guaranteed minimum EUR 4,000 (Region 3 minimum), increased to 13% of collected entry fees if higher (e.g. 144 players × EUR 230 × 13% = EUR 4,306). Any sponsor additions announced only once guaranteed in writing.
A8: Fee includes lunch every competition day, welcome kit, prize money, welcome and closing ceremonies, and on-course refreshments? | B8: Yes | C8: Yes | D8: =IF(C8="No","Optional",IF(B8<>"","Complete","Missing")) -> Complete | E8: Entry fee includes lunch on both competition days, welcome kit, prize money, welcome and closing ceremonies and on-course refreshments.
A9: Total meals included per player | B9: 2 | C9: Yes | D9: =IF(C9="No","Optional",IF(B9<>"","Complete","Missing")) -> Complete | E9: Lunch on 3 and 4 July, plus on-course refreshments and food/drink at the welcome and closing ceremonies.
A10: Payment schedule, cancellation and refund policy | B10: Full payment at registration. Cancellation by 1 June 2027: full refund minus EUR 20 admin fee; 2–20 June: 50% refund; after 20 June: no refund except documented medical reasons. | C10: Yes | D10: =IF(C10="No","Optional",IF(B10<>"","Complete","Missing")) -> Complete | E10: All charges in EUR. Optional hotel/transfer packages invoiced separately under the hotel's own terms.
A11: Primary accommodation rate | B11: Sheraton Rome Parco de' Medici (on site, walking distance to the course) – event rate to be agreed | C11: No | D11: =IF(C11="No","Optional",IF(B11<>"","Complete","Missing")) -> Optional | E11: Additional hotels in the EUR area and central Rome will be listed on the event page.
A12: Airport / local transport time to the course | B12: Fiumicino (FCO): approx. 12 km, 15–20 min by car. Ciampino (CIA): approx. 20 km, 30 min. Rome Termini: approx. 25–30 min. | C12: No | D12: =IF(C12="No","Optional",IF(B12<>"","Complete","Missing")) -> Optional | E12: Hotel and course are in the same complex (0 min). Paid shuttle service available from the hotel to the airports and city centre.

Sheet Media & Funding
A1: Media, Broadcasting & Funding
A2: Separate guaranteed commitments from proposed or conditional support.
A4: FIFG is close to finalizing an agreement with a major broadcasting company. Approximately 10 tournaments may be selected for live broadcasting, with an estimated production budget of about EUR 25,000 per selected tournament. Because the coverage may reach millions of viewers, bidders are encouraged to seek support from their national tourism board or sponsors.
A7: Requirement / question | B7: Bidder response | C7: Required? | D7: Status | E7: Evidence / comments
A8: Live-broadcast production plan and delivery partner | B8: Guaranteed: daily photography and social content, daily highlight video (min. 3 min) and an event aftermovie. Live streaming is an optional upgrade; production partner to be confirmed. | C8: Yes | D8: =IF(C8="No","Optional",IF(B8<>"","Complete","Missing")) -> Complete | E8: Media and Broadcast Lead appointed as the direct contact for FIFG Operations. Live scoring integrated with BlueGolf.
A9: Estimated broadcasting production budget (EUR) | B9: 25000 | C9: Yes | D9: =IF(C9="No","Optional",IF(B9<>"","Complete","Missing")) -> Complete | E9: Estimated cost of live broadcast production if selected under the FIFG broadcasting agreement (FIFG estimate).
A10: Can the bidder cover approximately EUR 25,000 in production costs if selected? (See note above.) | B10: Pending | C10: Yes | D10: =IF(C10="No","Optional",IF(B10<>"","Complete","Missing")) -> Complete | E10: Coverage depends on public-sector and sponsor funding, to be confirmed if the tournament is selected for broadcast.
A11: Guaranteed contribution toward broadcasting (EUR) | B11: 0 | C11: Yes | D11: =IF(C11="No","Optional",IF(B11<>"","Complete","Missing")) -> Complete | E11: No guaranteed amount at the submission date. Will be updated as soon as funding is confirmed in writing.
A12: Tourism board / public-sector funding possibilities | B12: Applications planned to Regione Lazio (sport and tourism events), Roma Capitale (major events, sport and tourism) and ENIT – Italian National Tourism Agency. | C12: Yes | D12: =IF(C12="No","Optional",IF(B12<>"","Complete","Missing")) -> Complete | E12: Rome is a global tourism destination; international broadcast reach supports the funding case.
A13: Sponsor funding approach and status | B13: Local and national sponsors to be approached after the award; in-kind support from the venue/hotel partner. Amounts promoted only once guaranteed in writing. | C13: Yes | D13: =IF(C13="No","Optional",IF(B13<>"","Complete","Missing")) -> Complete | E13: FIFG and event-partner branding on venue, accreditation, live scoring and digital content.
A14: Daily photography, social media, interviews and results graphics | B14: Yes – daily photography, social media posts, player interviews and daily results graphics. | C14: Yes | D14: =IF(C14="No","Optional",IF(B14<>"","Complete","Missing")) -> Complete | E14: Content published on Italian federation channels and supplied to FIFG.
A15: Daily video / highlights and event aftermovie deliverables | B15: Daily highlight video (min. 3 minutes) each competition day and an event aftermovie. | C15: Yes | D15: =IF(C15="No","Optional",IF(B15<>"","Complete","Missing")) -> Complete | E15: Daily highlights delivered by the evening of each competition day; aftermovie within 14 days of the event.
A16: Media archive, usage rights and content handover to FIFG | B16: Yes – full media archive and distribution rights handed over to FIFG. | C16: Yes | D16: =IF(C16="No","Optional",IF(B16<>"","Complete","Missing")) -> Complete | E16: Photos and videos delivered via shared folder within 14 days of the event.

Sheet Compliance & Variances
A1: Compliance & Variances
A2: Answer Yes or No for each applicable requirement. Use the evidence and comments columns to explain every No.
A4: A. Key requirement compliance
A5: Key requirement | B5: Yes / No | C5: Evidence | D5: Required? | E5: Status | F5: Comments
A6: Member Country is in good standing | D6: Yes | E6: =IF(D6="No","Not applicable",IF(B6="Yes","Complete",IF(B6="No","Variance","Missing"))) -> Missing
A7: No overdue FIFG debts at the submission deadline | D7: Yes | E7: =IF(D7="No","Not applicable",IF(B7="Yes","Complete",IF(B7="No","Variance","Missing"))) -> Missing
A8: Course quantity and quality meet the selected tournament level | B8: Yes | C8: Golf Club Parco de' Medici, Rome – 18-hole FootGolf layout on a 27-hole golf facility | D8: Yes | E8: =IF(D8="No","Not applicable",IF(B8="Yes","Complete",IF(B8="No","Variance","Missing"))) -> Complete | F8: FIFG 500 requires at least one fully equipped course.
A9: The main Open date was submitted by October 19, 2026 | D9: Yes | E9: =IF(D9="No","Not applicable",IF(B9="Yes","Complete",IF(B9="No","Variance","Missing"))) -> Missing
A10: If countries cannot resolve an Open-date clash, the country with more World Tour licences has priority | B10: Yes | C10: Bid document §3.1 | D10: Yes | E10: =IF(D10="No","Not applicable",IF(B10="Yes","Complete",IF(B10="No","Variance","Missing"))) -> Complete
A11: For FIFG 500 and above, the fee includes all required meals, kit, prize money, ceremonies and refreshments | B11: Yes | C11: Fees & Services sheet, rows 8–9 | D11: Yes | E11: =IF(D11="No","Not applicable",IF(B11="Yes","Complete",IF(B11="No","Variance","Missing"))) -> Complete
A12: Bidder will comply with FIFG rules, anti-doping requirements and approved local rules | B12: Yes | C12: Rules of the Game, World Tour and Competition Guidelines, anti-doping and approved local rules 2027 | D12: Yes | E12: =IF(D12="No","Not applicable",IF(B12="Yes","Complete",IF(B12="No","Variance","Missing"))) -> Complete
A13: Information and supporting evidence are accurate and authorized by the Member Country | D13: Yes | E13: =IF(D13="No","Not applicable",IF(B13="Yes","Complete",IF(B13="No","Variance","Missing"))) -> Missing

Sheet Comparison Summary
A1: FIFG 2027 Masters, Majors and 500 — Comparison Summary
A2: Submitted values populate automatically from the completed response sheets.
A4: A. Automatic bid snapshot
A5: Metric | B5: Submitted value | C5: Source
A6: Member Country | B6: =IF('Bidder Details'!B5="","",'Bidder Details'!B5) -> Italy | C6: Bidder Details
A7: FIFG region | B7: =IF('Bidder Details'!B6="","",'Bidder Details'!B6) -> Region 3 (Europe) | C7: Bidder Details
A8: Event level | B8: =IF('Bidder Details'!B7="","",'Bidder Details'!B7) -> FIFG 500 | C8: Bidder Details
A9: Host destination | B9: =IF('Bidder Details'!B9="","",'Bidder Details'!B9) -> Rome, Lazio, Italy – Golf Club Parco de' Medici | C9: Bidder Details
A10: Proposed start date | B10: =IF('Dates & Event'!B5="","",'Dates & Event'!B5) -> 2 July 2027 (official practice day) | C10: Dates & Event
A11: Main Open end date | B11: =IF('Dates & Event'!B6="","",'Dates & Event'!B6) -> 4 July 2027 | C11: Dates & Event
A12: Competition rounds | B12: =IF('Dates & Event'!B7="","",'Dates & Event'!B7) -> 2 | C12: Dates & Event
A13: Maximum field capacity | B13: =IF('Dates & Event'!B8="","",'Dates & Event'!B8) -> 144 | C13: Dates & Event
A14: World Tour licences in Member Country | B14: =IF('Bidder Details'!B12="","",'Bidder Details'!B12) | C14: Bidder Details
A15: Recreational licences | B15: =IF('Bidder Details'!B13="","",'Bidder Details'!B13) | C15: Bidder Details
A16: Women licences | B16: =IF('Bidder Details'!B14="","",'Bidder Details'!B14) | C16: Bidder Details
A17: Junior licences | B17: =IF('Bidder Details'!B15="","",'Bidder Details'!B15) | C17: Bidder Details
A18: Standard entry fee (EUR) | B18: =IF('Fees & Services'!B5="","",'Fees & Services'!B5) -> 230 | C18: Fees & Services
A19: Early-bird fee and validity | B19: =IF('Fees & Services'!B6="","",'Fees & Services'!B6) -> EUR 200 – early-bird valid 1–31 March 2027 | C19: Fees & Services
A20: Meals included per player | B20: =IF('Fees & Services'!B9="","",'Fees & Services'!B9) -> 2 | C20: Fees & Services
A21: Mandatory fee package included | B21: =IF('Fees & Services'!B8="","",'Fees & Services'!B8) -> Yes | C21: Fees & Services
A22: Prize money / prize fund (EUR) | B22: =IF('Fees & Services'!B7="","",'Fees & Services'!B7) -> 4000 | C22: Fees & Services
A23: Primary accommodation rate | B23: =IF('Fees & Services'!B11="","",'Fees & Services'!B11) -> Sheraton Rome Parco de' Medici (on site, walking distance to the course) – event rate to be agreed | C23: Fees & Services
A24: Airport / local transport time | B24: =IF('Fees & Services'!B12="","",'Fees & Services'!B12) -> Fiumicino (FCO): approx. 12 km, 15–20 min by car. Ciampino (CIA): approx. 20 km, 30 min. Rome Termini: approx. 25–30 min. | C24: Fees & Services
A25: Broadcast budget (EUR) | B25: =IF('Media & Funding'!B9="","",'Media & Funding'!B9) -> 25000 | C25: Media & Funding
A26: Broadcast contribution (EUR) | B26: =IF('Media & Funding'!B11="","",'Media & Funding'!B11) -> 0 | C26: Media & Funding
A27: Tourism board / public-sector funding | B27: =IF('Media & Funding'!B12="","",'Media & Funding'!B12) -> Applications planned to Regione Lazio (sport and tourism events), Roma Capitale (major events, sport and tourism) and ENIT – Italian National Tourism Agency. | C27: Media & Funding
A28: Sponsor funding | B28: =IF('Media & Funding'!B13="","",'Media & Funding'!B13) -> Local and national sponsors to be approached after the award; in-kind support from the venue/hotel partner. Amounts promoted only once guaranteed in writing. | C28: Media & Funding
A29: Declared variances | B29: ='Read Me & Status'!B21 -> 0 | C29: Read Me & Status
A30: Completion | B30: ='Read Me & Status'!D19 -> 0.75510204 | C30: Read Me & Status
A31: Readiness | B31: ='Read Me & Status'!B22 -> Outstanding items | C31: Read Me & Status
