Workbook

Sheet Piano di spesa
C1: PIANO DI SPESA · TAPPA ZERO
C2: 14–15 Novembre 2026 · Il Pelagone Hotel & Golf Resort, Gavorrano (GR)
C3: Associazione Italiana FootGolf · materiale da stampare e allestire · aggiornato al 28 ottobre 2026
B5: TOTALE BASE | D5: OPZIONALI | E5: TOTALE CON OPZIONALI | H5: VOCI DA DEFINIRE | J5: BUDGET DISPONIBILE | M5: RESIDUO SUL TOTALE BASE
B6: =SUMIFS($I$11:$I$30,$L$11:$L$30,"Sì") -> 3182.65 | D6: =SUMIFS($I$11:$I$30,$K$11:$K$30,"Opzionale",$L$11:$L$30,"No") -> 2000 | E6: =B6+D6 -> 5182.65 | H6: =COUNTIFS($K$11:$K$30,"Da definire") -> 4 | M6: =IF(J6="","",J6-B6)
B8: LEGENDA | C8: Celle gialle = da compilare (quantità, prezzi, fornitore, link, foto). Stato e Nel totale: menu a tendina. Il Totale si calcola da Q.tà × Prezzo unitario.
A10: N. | B10: AREA | C10: VOCE | D10: DESCRIZIONE / SPECIFICHE | E10: FORNITORE | F10: Q.TÀ | G10: UNITÀ | H10: PREZZO UNITARIO | I10: TOTALE | J10: IVA | K10: STATO | L10: NEL TOTALE | M10: ORDINE | N10: LINK | O10: FOTO | P10: NOTE
A11: 1 | B11: A · Stampa e comunicazione | C11: Pieghevole A4 | D11: 2 pieghe, 6 facciate, formato A4 (21 × 29,7 cm) orizzontale. | F11: 250 | G11: pz | H11: =71.65/250 -> 0.2866 | I11: =IF(OR(F11="",H11=""),"",F11*H11) -> 71.65 | J11: Inclusa | K11: Preventivo | L11: Sì | M11: Da ordinare | O11: incolla qui la foto | P11: Prezzo complessivo per 250 pezzi, IVA compresa.
A12: 2 | B12: A · Stampa e comunicazione | C12: Pieghevole A3 | D12: 2 pieghe, 6 facciate, formato A3 (29 × 42 cm) orizzontale. | F12: 250 | G12: pz | H12: =125.9/250 -> 0.5036 | I12: =IF(OR(F12="",H12=""),"",F12*H12) -> 125.9 | J12: Inclusa | K12: Alternativa | L12: No | M12: Da ordinare | O12: incolla qui la foto | P12: In alternativa al pieghevole A4 (n. 1): +€ 54,25 se si sceglie l'A3.
A13: 3 | B13: A · Stampa e comunicazione | C13: Flyer promozioni | D13: Flyer con le promozioni della stagione da distribuire in tappa. | G13: pz | I13: =IF(OR(F13="",H13=""),"",F13*H13) | J13: Da verificare | K13: Da definire | L13: Sì | M13: Da ordinare | O13: incolla qui la foto | P13: Prezzo e tiratura da definire.
A14: 4 | B14: A · Stampa e comunicazione | C14: Fiches personalizzate | D14: Una fiche per giocatore con il nome, usata in campo come ball marker. | F14: 200 | G14: pz | H14: 1.2 | I14: =IF(OR(F14="",H14=""),"",F14*H14) -> 240 | J14: Da verificare | K14: Preventivo | L14: Sì | M14: Da ordinare | O14: incolla qui la foto | P14: € 1,20 a fiche, prezzo trattabile al ribasso.
A15: 5 | B15: B · Allestimento del campo | C15: Bandiere doppio logo | D15: Bandiere di buca stampate con doppio logo. | E15: golflags.eu | F15: 1 | G15: fornitura | H15: 390 | I15: =IF(OR(F15="",H15=""),"",F15*H15) -> 390 | J15: Da verificare | K15: Preventivo | L15: Sì | M15: Da ordinare | N15: golflags.eu | O15: incolla qui la foto | P15: Verificare il numero di bandiere compreso nella fornitura.
A16: 6 | B16: B · Allestimento del campo | C16: Pannelli forex presentazione buca | D16: Forex 70 × 100 cm con vernice protettiva antigraffio, uno per buca. | F16: 18 | G16: pz | H16: =654/18 -> 36.333333 | I16: =IF(OR(F16="",H16=""),"",F16*H16) -> 654 | J16: Da verificare | K16: Preventivo | L16: Sì | M16: Da ordinare | O16: incolla qui la foto | P16: € 654 per i 18 pezzi.
A17: 7 | B17: B · Allestimento del campo | C17: Partenze forex Women e Junior | D17: Segnaletica in forex per le partenze dedicate Women e Junior. | G17: pz | I17: =IF(OR(F17="",H17=""),"",F17*H17) | J17: Da verificare | K17: Da definire | L17: Sì | M17: Da ordinare | O17: incolla qui la foto | P17: Quantità e prezzo da definire.
A18: 8 | B18: B · Allestimento del campo | C18: Mini vele di partenza | D18: Mini vele per la partenza di ogni singola buca, stile Open internazionale. | F18: 1 | G18: fornitura | H18: 2000 | I18: =IF(OR(F18="",H18=""),"",F18*H18) -> 2000 | J18: Da verificare | K18: Opzionale | L18: No | M18: Da ordinare | O18: incolla qui la foto | P18: Voce eventuale: fuori dal totale base.
A19: 9 | B19: C · Immagine, media e presentazione | C19: Wall per foto giocatori | D19: Fondale pubblicitario 300 × 240 cm per le foto dei giocatori. | F19: 1 | G19: pz | H19: 579 | I19: =IF(OR(F19="",H19=""),"",F19*H19) -> 579 | J19: Da verificare | K19: Preventivo | L19: Sì | M19: Da ordinare | O19: incolla qui la foto
A20: 10 | B20: C · Immagine, media e presentazione | C20: Telo per videoproiettore | D20: Telo da 120 pollici per la presentazione AIFG. | E20: Amazon | F20: 1 | G20: pz | H20: 100 | I20: =IF(OR(F20="",H20=""),"",F20*H20) -> 100 | J20: Da verificare | K20: Stima | L20: Sì | M20: Da ordinare | N20: amazon.it | O20: incolla qui la foto | P20: Prezzo fra € 80 e € 100: messo il massimo per prudenza.
A21: 11 | B21: C · Immagine, media e presentazione | C21: Drone per riprese e diretta live | D21: DJI Mini 4 Pro o Mini 5 Pro per riprese aeree e diretta streaming della tappa. | F21: 1 | G21: pz | H21: 700 | I21: =IF(OR(F21="",H21=""),"",F21*H21) -> 700 | J21: Da verificare | K21: Stima | L21: Sì | M21: Da ordinare | O21: incolla qui la foto | P21: € 400–700 secondo modello e kit: messo il massimo per prudenza.
A22: 12 | B22: C · Immagine, media e presentazione | C22: Tovaglia tavolo presentazione AIFG | D22: Tovaglia personalizzata per il tavolo della presentazione AIFG. | F22: 1 | G22: pz | I22: =IF(OR(F22="",H22=""),"",F22*H22) | J22: Da verificare | K22: Da definire | L22: Sì | M22: Da ordinare | O22: incolla qui la foto | P22: Prezzo da richiedere.
A23: 13 | B23: D · Accoglienza e punto ristoro | C23: Tavoli pieghevoli | D23: Tavolo pieghevole 180 × 70 × 74 cm, bianco. | F23: 4 | G23: pz | H23: 37 | I23: =IF(OR(F23="",H23=""),"",F23*H23) -> 148 | J23: Da verificare | K23: Stima | L23: Sì | M23: Da ordinare | O23: incolla qui la foto | P23: € 37 a tavolo. Quantità di 4 ipotizzata: da confermare.
A24: 14 | B24: D · Accoglienza e punto ristoro | C24: Tovaglie tavoli ristoro | D24: Tovaglie per i tavoli del punto ristoro. | F24: 4 | G24: pz | I24: =IF(OR(F24="",H24=""),"",F24*H24) | J24: Da verificare | K24: Da definire | L24: Sì | M24: Da ordinare | O24: incolla qui la foto | P24: Costo da verificare.
A25: 15 | B25: D · Accoglienza e punto ristoro | C25: Ragazze immagine | D25: Servizio di ragazze immagine per l'accoglienza e le premiazioni del weekend. | F25: 1 | G25: servizio | H25: 300 | I25: =IF(OR(F25="",H25=""),"",F25*H25) -> 300 | J25: Da verificare | K25: Preventivo | L25: Sì | M25: Da ordinare | O25: incolla qui la foto
A26: 16 | I26: =IF(OR(F26="",H26=""),"",F26*H26) | O26: incolla qui la foto
A27: 17 | I27: =IF(OR(F27="",H27=""),"",F27*H27) | O27: incolla qui la foto
A28: 18 | I28: =IF(OR(F28="",H28=""),"",F28*H28) | O28: incolla qui la foto
A29: 19 | I29: =IF(OR(F29="",H29=""),"",F29*H29) | O29: incolla qui la foto
A30: 20 | I30: =IF(OR(F30="",H30=""),"",F30*H30) | O30: incolla qui la foto
C31: TOTALE BASE (voci «Nel totale» = Sì) | I31: =SUMIFS($I$11:$I$30,$L$11:$L$30,"Sì") -> 3182.65
B33: Note
B34: • Pieghevole A4 (n. 1) e A3 (n. 2) sono alternativi: nel totale base c'è l'A4. Per passare all'A3 invertire «Nel totale» sulle due righe.
B35: • Mini vele (n. 8) è voce eventuale, fuori dal totale base. Telo proiettore (€ 80–100) e drone (€ 400–700): messo il massimo per prudenza.
B36: • Tavoli ristoro: quantità 4 ipotizzata, da confermare. IVA indicata come inclusa solo dove il preventivo lo dice esplicitamente.
B37: • Foto: in Excel 365 selezionare la cella gialla → Inserisci → Immagini → Inserisci nella cella. Le righe libere in fondo sono pronte per nuove voci.

Sheet Riepilogo per area
B1: RIEPILOGO PER AREA
B2: Tappa Zero · 14–15 Novembre 2026
B4: AREA | C4: N. VOCI | D4: TOTALE BASE | E4: OPZIONALI | F4: TOTALE | G4: % BASE
A5: A | B5: Stampa e comunicazione | C5: =COUNTIFS('Piano di spesa'!$B$11:$B$30,"A · Stampa e comunicazione") -> 4 | D5: =SUMIFS('Piano di spesa'!$I$11:$I$30,'Piano di spesa'!$B$11:$B$30,"A · Stampa e comunicazione",'Piano di spesa'!$L$11:$L$30,"Sì") -> 311.65 | E5: =SUMIFS('Piano di spesa'!$I$11:$I$30,'Piano di spesa'!$B$11:$B$30,"A · Stampa e comunicazione",'Piano di spesa'!$K$11:$K$30,"Opzionale",'Piano di spesa'!$L$11:$L$30,"No") -> 0 | F5: =D5+E5 -> 311.65 | G5: =IF($D$9=0,0,D5/$D$9) -> 0.097921543
A6: B | B6: Allestimento del campo | C6: =COUNTIFS('Piano di spesa'!$B$11:$B$30,"B · Allestimento del campo") -> 4 | D6: =SUMIFS('Piano di spesa'!$I$11:$I$30,'Piano di spesa'!$B$11:$B$30,"B · Allestimento del campo",'Piano di spesa'!$L$11:$L$30,"Sì") -> 1044 | E6: =SUMIFS('Piano di spesa'!$I$11:$I$30,'Piano di spesa'!$B$11:$B$30,"B · Allestimento del campo",'Piano di spesa'!$K$11:$K$30,"Opzionale",'Piano di spesa'!$L$11:$L$30,"No") -> 2000 | F6: =D6+E6 -> 3044 | G6: =IF($D$9=0,0,D6/$D$9) -> 0.32802853
A7: C | B7: Immagine, media e presentazione | C7: =COUNTIFS('Piano di spesa'!$B$11:$B$30,"C · Immagine, media e presentazione") -> 4 | D7: =SUMIFS('Piano di spesa'!$I$11:$I$30,'Piano di spesa'!$B$11:$B$30,"C · Immagine, media e presentazione",'Piano di spesa'!$L$11:$L$30,"Sì") -> 1379 | E7: =SUMIFS('Piano di spesa'!$I$11:$I$30,'Piano di spesa'!$B$11:$B$30,"C · Immagine, media e presentazione",'Piano di spesa'!$K$11:$K$30,"Opzionale",'Piano di spesa'!$L$11:$L$30,"No") -> 0 | F7: =D7+E7 -> 1379 | G7: =IF($D$9=0,0,D7/$D$9) -> 0.43328673
A8: D | B8: Accoglienza e punto ristoro | C8: =COUNTIFS('Piano di spesa'!$B$11:$B$30,"D · Accoglienza e punto ristoro") -> 3 | D8: =SUMIFS('Piano di spesa'!$I$11:$I$30,'Piano di spesa'!$B$11:$B$30,"D · Accoglienza e punto ristoro",'Piano di spesa'!$L$11:$L$30,"Sì") -> 448 | E8: =SUMIFS('Piano di spesa'!$I$11:$I$30,'Piano di spesa'!$B$11:$B$30,"D · Accoglienza e punto ristoro",'Piano di spesa'!$K$11:$K$30,"Opzionale",'Piano di spesa'!$L$11:$L$30,"No") -> 0 | F8: =D8+E8 -> 448 | G8: =IF($D$9=0,0,D8/$D$9) -> 0.1407632
B9: TOTALE | C9: =SUM(C5:C8) -> 15 | D9: =SUM(D5:D8) -> 3182.65 | E9: =SUM(E5:E8) -> 2000 | F9: =SUM(F5:F8) -> 5182.65 | G9: =IF($D$9=0,0,SUM(G5:G8)) -> 1
